{
	"Benchmark.sol": 7059,
	"BenchmarkAaveForge.sol": 19546,
	"BenchmarkData.sol": 4976,
	"BenchmarkGovernance.sol": 12051,
	"BenchmarkMarket.sol": 17144,
	"BenchmarkMarketFactory.sol": 21860,
	"BenchmarkTreasury.sol": 3239,
	"DateUtils.sol": 2372,
	"Factory.sol": 86,
	"Math.sol": 86,
	"UIntUtils.sol": 86,
	"Utils.sol": 86,
	"MockBenchmark.sol": 7059,
	"MockGovernance.sol": 12051,
	"MockTreasury.sol": 3239,
	"TestToken.sol": 2546,
	"Timelock.sol": 6025,
	"TestUsdtTransferFrom.sol": 280,
	"BMK.sol": 5975,
	"BenchmarkFutureYieldToken.sol": 3621,
	"BenchmarkOwnershipToken.sol": 3228,
	"WETH9.sol": 1764
}